[
  {
    "repo": "https://github.com/disarm-platform/fn-bvbd",
    "uses-ref": [
      "reccDWpNMk4L5MHGi"
    ],
    "function_name": "fn-bvbd",
    "uses": [
      "Not sure"
    ],
    "scale_to_zero": true,
    "hide_from_deploy": true
  },
  {
    "repo": "https://github.com/disarm-platform/fn-prevalence-predictor-spaMM",
    "dev_notes": "`use-template` branch needs to be merged",
    "function_name": "fn-prevalence-predictor-spamm",
    "scale_to_zero": true
  },
  {
    "repo": "https://github.com/disarm-platform/fn-prevalence-predictor",
    "dev_notes": "`use-template` branch needs to be merged",
    "ui_repo": "https://github.com/disarm-platform/ntd-shiny and https://github.com/disarm-platform/ntd-shiny-points",
    "ui": "https://disarm.shinyapps.io/ntd-shiny-points/",
    "uses-ref": [
      "rec9sU4npKwq4Fgeg"
    ],
    "function_name": "fn-prevalence-predictor",
    "uses": [
      "NTD survey tool"
    ],
    "scale_to_zero": true
  },
  {
    "repo": "https://github.com/disarm-platform/fn-dbscan-clusterer",
    "ui_repo": "https://github.com/disarm-platform/ui-dbscan-clusterer",
    "ui": "https://disarm.shinyapps.io/ui-dbscan-clusterer",
    "uses-ref": [
      "recGyEuJx8BRjIIa8"
    ],
    "function_name": "fn-dbscan-clusterer",
    "uses": [
      "Reveal targeting "
    ],
    "scale_to_zero": true
  },
  {
    "repo": "https://github.com/disarm-platform/fn-raster-vector-summary-stats",
    "dev_notes": "Replace with enhanced version after testing",
    "ui_repo": "https://github.com/disarm-platform/ui-raster-vector-summary-stats",
    "ui": "https://disarm.shinyapps.io/ui-raster-vector-summary-stats/",
    "uses-ref": [
      "recRmnTB4GtOu9Pev"
    ],
    "function_name": "fn-raster-vector-summary-stats",
    "uses": [
      "Reveal tool"
    ],
    "scale_to_zero": true
  },
  {
    "repo": "https://github.com/disarm-platform/fn-bvbd-forecast",
    "function_name": "fn-bvbd-forecast",
    "image_version": "disarm/fn-bvbd:0.0.1",
    "scale_to_zero": true
  },
  {
    "repo": "https://github.com/disarm-platform/fn-cv-hal",
    "function_name": "fn-cv-hal",
    "image_version": "disarm/fn-cv-ml:0.0.6",
    "scale_to_zero": true
  },
  {
    "repo": "https://github.com/disarm-platform/fn-covariate-extractor",
    "dev_notes": "added squid; `use-template` branch needs to be merged",
    "ui_repo": "https://github.com/disarm-platform/ui-covariate-extractor",
    "ui": "https://disarm.shinyapps.io/ui-covariate-extractor",
    "uses-ref": [
      "recvPV9U4m7NPhPmV"
    ],
    "function_name": "fn-covariate-extractor",
    "uses": [
      "Not sure"
    ],
    "scale_to_zero": true
  },
  {
    "repo": "https://github.com/disarm-platform/fn-adaptive-sampling",
    "dev_notes": "`use-template` branch needs to be merged",
    "uses-ref": [
      "recHroWPf3qc4yDKy"
    ],
    "function_name": "fn-adaptive-sampling",
    "uses": [
      "NTD survey tool"
    ],
    "scale_to_zero": true,
    "test_req": "{}\n"
  },
  {
    "repo": "https://github.com/disarm-dev/fn-hotspot-gears",
    "function_name": "fn-hotspot-gears",
    "scale_to_zero": true
  },
  {
    "repo": "https://github.com/disarm-platform/fn-cv-ml",
    "function_name": "fn-cv-ml",
    "scale_to_zero": true
  },
  {
    "repo": "https://github.com/disarm-platform/fn-ppmify",
    "function_name": "fn-ppmify",
    "scale_to_zero": true
  },
  {
    "repo": "https://github.com/disarm-platform/fn-village-finder",
    "ui_repo": "https://github.com/disarm-platform/fn-village-finder",
    "ui": "https://disarm.shinyapps.io/ui-village-finder/",
    "uses-ref": [
      "recKYrSJZj8bey85B"
    ],
    "function_name": "fn-village-finder",
    "uses": [
      "Not sure"
    ],
    "scale_to_zero": true
  },
  {
    "repo": "https://github.com/disarm-platform/fn-raster-vector-summary-stats-enhanced",
    "dev_notes": "`use-template` branch needs to be merged",
    "function_name": "fn-raster-vector-summary-stats-enhanced",
    "scale_to_zero": true
  }
]